fluxative-0.1.5.dist-info/licenses/LICENSE
src/__init__.py
src/_version.py
src/converter.py
src/expander.py
src/fluxative.py
fluxative-0.1.5.dist-info/METADATA
fluxative-0.1.5.dist-info/WHEEL
fluxative-0.1.5.dist-info/entry_points.txt
fluxative-0.1.5.dist-info/top_level.txt
fluxative-0.1.5.dist-info/RECORD
