Metadata-Version: 2.4
Name: fluxative
Version: 0.1.5
Summary: Generate LLM context files from Git repositories
Author: JakePIXL
License: MIT
Project-URL: Homepage, https://github.com/JakePIXL/fluxative
Project-URL: Repository, https://github.com/JakePIXL/fluxative
Project-URL: Issues, https://github.com/JakePIXL/fluxative/issues
Project-URL: Changelog, https://github.com/JakePIXL/fluxative/releases
Requires-Python: >=3.10
License-File: LICENSE
Requires-Dist: gitingest>=0.1.4
Requires-Dist: typer>=0.15.2
Provides-Extra: dev
Requires-Dist: pytest>=7.0.0; extra == "dev"
Requires-Dist: ruff>=0.9.10; extra == "dev"
Dynamic: license-file
